athena/README.md
athena/__init__.py
athena/__main__.py
athena/cache.py
athena/cli.py
athena/config.py
athena/docstring_updater.py
athena/entity_path.py
athena/hashing.py
athena/info.py
athena/locate.py
athena/mcp_config.py
athena/mcp_server.py
athena/models.py
athena/module_docstring_updater.py
athena/package_utils.py
athena/repository.py
athena/search.py
athena/status.py
athena/sync.py
athena/parsers/__init__.py
athena/parsers/base.py
athena/parsers/python_parser.py
athena_code-1.0.0.dist-info/licenses/LICENSE
athena_code-1.0.0.dist-info/METADATA
athena_code-1.0.0.dist-info/WHEEL
athena_code-1.0.0.dist-info/entry_points.txt
athena_code-1.0.0.dist-info/top_level.txt
athena_code-1.0.0.dist-info/RECORD
