Metadata-Version: 2.4
Name: athena-code
Version: 1.0.0
Summary: A semantic code analysis tool designed to help Claude Code navigate repositories efficiently while dramatically reducing token consumption.
Requires-Python: >=3.12
License-File: LICENSE
Requires-Dist: typer>=0.12.0
Requires-Dist: tree-sitter>=0.21.0
Requires-Dist: tree-sitter-python>=0.21.0
Requires-Dist: mcp>=1.0.0
Requires-Dist: rich>=14.2.0
Requires-Dist: pyyaml>=6.0
Provides-Extra: dev
Requires-Dist: build; extra == "dev"
Requires-Dist: pytest>=7.0; extra == "dev"
Requires-Dist: pytest-cov>=4.0; extra == "dev"
Requires-Dist: pytest-asyncio>=0.23.0; extra == "dev"
Requires-Dist: tasktree; extra == "dev"
Dynamic: license-file
